CHANGELOG.txt
LICENCE.txt
MANIFEST.in
README.txt
setup.py
uweaimevan_basic_calculator/__init__.py
uweaimevan_basic_calculator/app.py
uweaimevan_basic_calculator.egg-info/PKG-INFO
uweaimevan_basic_calculator.egg-info/SOURCES.txt
uweaimevan_basic_calculator.egg-info/dependency_links.txt
uweaimevan_basic_calculator.egg-info/top_level.txt